lintreview/__init__.py
lintreview/cli.py
lintreview/config.py
lintreview/diff.py
lintreview/docker.py
lintreview/git.py
lintreview/github.py
lintreview/processor.py
lintreview/repo.py
lintreview/review.py
lintreview/tasks.py
lintreview/web.py
lintreview/fixers/__init__.py
lintreview/fixers/commit_strategy.py
lintreview/fixers/error.py
lintreview/tools/__init__.py
lintreview/tools/ansible.py
lintreview/tools/black.py
lintreview/tools/checkstyle.py
lintreview/tools/commitcheck.py
lintreview/tools/credo.py
lintreview/tools/csslint.py
lintreview/tools/eslint.py
lintreview/tools/flake8.py
lintreview/tools/foodcritic.py
lintreview/tools/golint.py
lintreview/tools/goodcheck.py
lintreview/tools/gpg.py
lintreview/tools/jshint.py
lintreview/tools/jsonlint.py
lintreview/tools/ktlint.py
lintreview/tools/luacheck.py
lintreview/tools/mypy.py
lintreview/tools/pep8.py
lintreview/tools/phpcs.py
lintreview/tools/phpmd.py
lintreview/tools/puppet.py
lintreview/tools/py3k.py
lintreview/tools/pytype.py
lintreview/tools/remarklint.py
lintreview/tools/rubocop.py
lintreview/tools/sasslint.py
lintreview/tools/shellcheck.py
lintreview/tools/standardjs.py
lintreview/tools/stylelint.py
lintreview/tools/swiftlint.py
lintreview/tools/tslint.py
lintreview/tools/yamllint.py
lintreview-2.37.3.dist-info/LICENSE
lintreview-2.37.3.dist-info/METADATA
lintreview-2.37.3.dist-info/WHEEL
lintreview-2.37.3.dist-info/entry_points.txt
lintreview-2.37.3.dist-info/top_level.txt
lintreview-2.37.3.dist-info/RECORD
