Metadata-Version: 2.1
Name: lintreview
Version: 2.37.3
Summary: Lint Review, an automated code review tool that integrates with github. Integrates with the github API & a variety of code checking tools.
Home-page: UNKNOWN
Author: Mark Story
Author-email: mark@mark-story.com
License: UNKNOWN
Platform: UNKNOWN
Requires-Dist: Flask (==1.1.1)
Requires-Dist: github3.py (==1.3.0)
Requires-Dist: celery (==4.3.0)
Requires-Dist: vine (==1.3.0)
Requires-Dist: gunicorn (==19.5.0)
Requires-Dist: argparse (<=1.3.0,>=1.2.0)
Requires-Dist: jprops (==2.0.2)
Requires-Dist: docker (==3.7.1)
Requires-Dist: requests (<3.0.0,>=2.21.0)
Requires-Dist: typing (==3.6.6)
